{"data":{"Year":[2014,2015,2016,2017,2018,2019,2020,2021,2022,2016,2017,2018,2019,2020,2021,2022],"Series":["AG_LND_FOVH","AG_LND_FOVH","AG_LND_FOVH","AG_LND_FOVH","AG_LND_FOVH","AG_LND_FOVH","AG_LND_FOVH","AG_LND_FOVH","AG_LND_FOVH","AG_LND_NFI","AG_LND_NFI","AG_LND_NFI","AG_LND_NFI","AG_LND_NFI","AG_LND_NFI","AG_LND_NFI"],"Units":["PT","PT","PT","PT","PT","PT","PT","PT","PT","PT","PT","PT","PT","PT","PT","PT"],"Value":[27.7,30.2,20.5,24.6,23.5,28.4,18.4,16.8,16.9,98.8,97.7,99.1,99.9,99.8,99.4,97.8]},"edges":[]}