{
  "resources": [
    {
      "path": "data.csv",
      "name": "data",
      "profile": "tabular-data-resource",
      "scheme": "file",
      "format": "csv",
      "hashing": "md5",
      "encoding": "utf-8",
      "schema": {
        "fields": [
          {
            "name": "Year",
            "type": "number",
            "title": "Urtea"
          },
          {
            "name": "Value",
            "type": "number",
            "title": "Balioa"
          }
        ]
      }
    }
  ],
  "profile": "data-package",
  "name": "5-6-1",
  "title": "Sexu-harremanei, antisorgailuen erabilerari eta ugalketa-osasunari buruzko erabaki informatuak hartzen dituzten 15 eta 49 urte bitarteko emakumeen proportzioa"
}