[{"Year":2016,"Value":19.2,"Units":"Kg per hectare","Series":"Ammonia emissions from agriculture and livestock per hectare"},{"Year":2019,"Value":18.4,"Units":"Kg per hectare","Series":"Ammonia emissions from agriculture and livestock per hectare"},{"Year":2020,"Value":18.5,"Units":"Kg per hectare","Series":"Ammonia emissions from agriculture and livestock per hectare"},{"Year":2013,"Value":18.6,"Units":"Kg per hectare","Series":"Ammonia emissions from agriculture and livestock per hectare"},{"Year":2021,"Value":18.1,"Units":"Kg per hectare","Series":"Ammonia emissions from agriculture and livestock per hectare"},{"Year":2015,"Value":19.1,"Units":"Kg per hectare","Series":"Ammonia emissions from agriculture and livestock per hectare"},{"Year":2018,"Value":18.2,"Units":"Kg per hectare","Series":"Ammonia emissions from agriculture and livestock per hectare"},{"Year":2017,"Value":19.2,"Units":"Kg per hectare","Series":"Ammonia emissions from agriculture and livestock per hectare"},{"Year":2011,"Value":18.6,"Units":"Kg per hectare","Series":"Ammonia emissions from agriculture and livestock per hectare"},{"Year":2012,"Value":19.2,"Units":"Kg per hectare","Series":"Ammonia emissions from agriculture and livestock per hectare"},{"Year":2010,"Value":19.6,"Units":"Kg per hectare","Series":"Ammonia emissions from agriculture and livestock per hectare"},{"Year":2014,"Value":19.3,"Units":"Kg per hectare","Series":"Ammonia emissions from agriculture and livestock per hectare"},{"Year":2022,"Value":18.0,"Units":"Kg per hectare","Series":"Ammonia emissions from agriculture and livestock per hectare"},{"Year":2016,"Value":4.2,"Units":"Kilotons","Series":"Ammonia emissions from agriculture and livestock"},{"Year":2013,"Value":4.1,"Units":"Kilotons","Series":"Ammonia emissions from agriculture and livestock"},{"Year":2022,"Value":4.0,"Units":"Kilotons","Series":"Ammonia emissions from agriculture and livestock"},{"Year":2017,"Value":4.3,"Units":"Kilotons","Series":"Ammonia emissions from agriculture and livestock"},{"Year":2019,"Value":4.1,"Units":"Kilotons","Series":"Ammonia emissions from agriculture and livestock"},{"Year":2014,"Value":4.3,"Units":"Kilotons","Series":"Ammonia emissions from agriculture and livestock"},{"Year":2020,"Value":4.1,"Units":"Kilotons","Series":"Ammonia emissions from agriculture and livestock"},{"Year":2012,"Value":4.2,"Units":"Kilotons","Series":"Ammonia emissions from agriculture and livestock"},{"Year":2011,"Value":4.1,"Units":"Kilotons","Series":"Ammonia emissions from agriculture and livestock"},{"Year":2021,"Value":4.0,"Units":"Kilotons","Series":"Ammonia emissions from agriculture and livestock"},{"Year":2010,"Value":4.3,"Units":"Kilotons","Series":"Ammonia emissions from agriculture and livestock"},{"Year":2018,"Value":4.0,"Units":"Kilotons","Series":"Ammonia emissions from agriculture and livestock"},{"Year":2015,"Value":4.2,"Units":"Kilotons","Series":"Ammonia emissions from agriculture and livestock"}]