[{"Year":2019,"Value":3.57,"Units":"PER_1000_LIVE_BIRTHS"},{"Year":2021,"Value":2.95,"Units":"PER_1000_LIVE_BIRTHS"},{"Year":2023,"Value":3.12,"Units":"PER_1000_LIVE_BIRTHS"},{"Year":2020,"Value":3.05,"Units":"PER_1000_LIVE_BIRTHS"},{"Year":2022,"Value":3.59,"Units":"PER_1000_LIVE_BIRTHS"},{"Year":2010,"Value":3.5,"Units":"PER_1000_LIVE_BIRTHS"},{"Year":2016,"Value":3.18,"Units":"PER_1000_LIVE_BIRTHS"},{"Year":2013,"Value":2.77,"Units":"PER_1000_LIVE_BIRTHS"},{"Year":2014,"Value":2.89,"Units":"PER_1000_LIVE_BIRTHS"},{"Year":2017,"Value":2.75,"Units":"PER_1000_LIVE_BIRTHS"},{"Year":2015,"Value":3.45,"Units":"PER_1000_LIVE_BIRTHS"},{"Year":2011,"Value":3.35,"Units":"PER_1000_LIVE_BIRTHS"},{"Year":2012,"Value":3.17,"Units":"PER_1000_LIVE_BIRTHS"},{"Year":2018,"Value":3.6,"Units":"PER_1000_LIVE_BIRTHS"}]