[{"Year":2010,"Value":15.6,"Units":"PT"},{"Year":2011,"Value":15.0,"Units":"PT"},{"Year":2012,"Value":13.9,"Units":"PT"},{"Year":2013,"Value":15.3,"Units":"PT"},{"Year":2014,"Value":16.0,"Units":"PT"},{"Year":2015,"Value":14.5,"Units":"PT"},{"Year":2016,"Value":15.7,"Units":"PT"},{"Year":2017,"Value":14.4,"Units":"PT"},{"Year":2018,"Value":17.8,"Units":"PT"},{"Year":2019,"Value":17.8,"Units":"PT"},{"Year":2020,"Value":19.8,"Units":"PT"},{"Year":2021,"Value":20.2,"Units":"PT"},{"Year":2022,"Value":18.2,"Units":"PT"},{"Year":2023,"Value":20.4,"Units":"PT"}]