[{"Year":2013,"Value":3.8,"Units":"Per 100,000 employees","Series":"Fatal occupational injuries"},{"Year":2021,"Value":3.7,"Units":"Per 100,000 employees","Series":"Fatal occupational injuries"},{"Year":2018,"Value":4.0,"Units":"Per 100,000 employees","Series":"Fatal occupational injuries"},{"Year":2019,"Value":3.2,"Units":"Per 100,000 employees","Series":"Fatal occupational injuries"},{"Year":2017,"Value":3.5,"Units":"Per 100,000 employees","Series":"Fatal occupational injuries"},{"Year":2016,"Value":4.4,"Units":"Per 100,000 employees","Series":"Fatal occupational injuries"},{"Year":2022,"Value":3.1,"Units":"Per 100,000 employees","Series":"Fatal occupational injuries"},{"Year":2015,"Value":3.7,"Units":"Per 100,000 employees","Series":"Fatal occupational injuries"},{"Year":2020,"Value":2.9,"Units":"Per 100,000 employees","Series":"Fatal occupational injuries"},{"Year":2014,"Value":3.4,"Units":"Per 100,000 employees","Series":"Fatal occupational injuries"},{"Year":2024,"Value":2.7,"Units":"Per 100,000 employees","Series":"Fatal occupational injuries"},{"Year":2023,"Value":3.1,"Units":"Per 100,000 employees","Series":"Fatal occupational injuries"},{"Year":2018,"Value":3627.1,"Units":"Per 100,000 employees","Series":"Non-fatal occupational injuries"},{"Year":2013,"Value":3158.0,"Units":"Per 100,000 employees","Series":"Non-fatal occupational injuries"},{"Year":2023,"Value":3697.8,"Units":"Per 100,000 employees","Series":"Non-fatal occupational injuries"},{"Year":2014,"Value":3187.0,"Units":"Per 100,000 employees","Series":"Non-fatal occupational injuries"},{"Year":2017,"Value":3645.2,"Units":"Per 100,000 employees","Series":"Non-fatal occupational injuries"},{"Year":2021,"Value":3702.3,"Units":"Per 100,000 employees","Series":"Non-fatal occupational injuries"},{"Year":2022,"Value":3790.0,"Units":"Per 100,000 employees","Series":"Non-fatal occupational injuries"},{"Year":2015,"Value":3374.8,"Units":"Per 100,000 employees","Series":"Non-fatal occupational injuries"},{"Year":2016,"Value":3489.4,"Units":"Per 100,000 employees","Series":"Non-fatal occupational injuries"},{"Year":2020,"Value":3247.4,"Units":"Per 100,000 employees","Series":"Non-fatal occupational injuries"},{"Year":2024,"Value":3875.6,"Units":"Per 100,000 employees","Series":"Non-fatal occupational injuries"},{"Year":2019,"Value":3897.8,"Units":"Per 100,000 employees","Series":"Non-fatal occupational injuries"}]