[{"Year":2015,"Value":14537114.2400000002,"Units":"T","Series":"EN_ATM_CO2"},{"Year":2011,"Value":14931958.2400000002,"Units":"T","Series":"EN_ATM_CO2"},{"Year":2012,"Value":15792128.7699999996,"Units":"T","Series":"EN_ATM_CO2"},{"Year":2020,"Value":13639720.4900000002,"Units":"T","Series":"EN_ATM_CO2"},{"Year":2017,"Value":15166249.8800000008,"Units":"T","Series":"EN_ATM_CO2"},{"Year":2021,"Value":14760223.1199999992,"Units":"T","Series":"EN_ATM_CO2"},{"Year":2022,"Value":15802683.9100000001,"Units":"T","Series":"EN_ATM_CO2"},{"Year":2019,"Value":15484145.5299999993,"Units":"T","Series":"EN_ATM_CO2"},{"Year":2018,"Value":14723125.0899999999,"Units":"T","Series":"EN_ATM_CO2"},{"Year":2014,"Value":14251428.5700000003,"Units":"T","Series":"EN_ATM_CO2"},{"Year":2023,"Value":13605046.2400000002,"Units":"T","Series":"EN_ATM_CO2"},{"Year":2010,"Value":16684857.8499999996,"Units":"T","Series":"EN_ATM_CO2"},{"Year":2013,"Value":14391247.3699999992,"Units":"T","Series":"EN_ATM_CO2"},{"Year":2016,"Value":14504152.6099999994,"Units":"T","Series":"EN_ATM_CO2"},{"Year":2010,"Value":0.22,"Units":"KG_CO2_PER_GDP_EUR","Series":"EN_ATM_CO2GDP"},{"Year":2011,"Value":0.2,"Units":"KG_CO2_PER_GDP_EUR","Series":"EN_ATM_CO2GDP"},{"Year":2012,"Value":0.21,"Units":"KG_CO2_PER_GDP_EUR","Series":"EN_ATM_CO2GDP"},{"Year":2013,"Value":0.2,"Units":"KG_CO2_PER_GDP_EUR","Series":"EN_ATM_CO2GDP"},{"Year":2014,"Value":0.19,"Units":"KG_CO2_PER_GDP_EUR","Series":"EN_ATM_CO2GDP"},{"Year":2022,"Value":0.18,"Units":"KG_CO2_PER_GDP_EUR","Series":"EN_ATM_CO2GDP"},{"Year":2015,"Value":0.19,"Units":"KG_CO2_PER_GDP_EUR","Series":"EN_ATM_CO2GDP"},{"Year":2018,"Value":0.18,"Units":"KG_CO2_PER_GDP_EUR","Series":"EN_ATM_CO2GDP"},{"Year":2016,"Value":0.18,"Units":"KG_CO2_PER_GDP_EUR","Series":"EN_ATM_CO2GDP"},{"Year":2019,"Value":0.18,"Units":"KG_CO2_PER_GDP_EUR","Series":"EN_ATM_CO2GDP"},{"Year":2020,"Value":0.18,"Units":"KG_CO2_PER_GDP_EUR","Series":"EN_ATM_CO2GDP"},{"Year":2021,"Value":0.18,"Units":"KG_CO2_PER_GDP_EUR","Series":"EN_ATM_CO2GDP"},{"Year":2017,"Value":0.19,"Units":"KG_CO2_PER_GDP_EUR","Series":"EN_ATM_CO2GDP"},{"Year":2023,"Value":0.15,"Units":"KG_CO2_PER_GDP_EUR","Series":"EN_ATM_CO2GDP"},{"Year":2010,"Value":0.43,"Units":"KG_CO2_PER_GDP_EUR","Series":"EN_ATM_CO2MVA"},{"Year":2011,"Value":0.41,"Units":"KG_CO2_PER_GDP_EUR","Series":"EN_ATM_CO2MVA"},{"Year":2012,"Value":0.4,"Units":"KG_CO2_PER_GDP_EUR","Series":"EN_ATM_CO2MVA"},{"Year":2013,"Value":0.41,"Units":"KG_CO2_PER_GDP_EUR","Series":"EN_ATM_CO2MVA"},{"Year":2014,"Value":0.38,"Units":"KG_CO2_PER_GDP_EUR","Series":"EN_ATM_CO2MVA"},{"Year":2015,"Value":0.37,"Units":"KG_CO2_PER_GDP_EUR","Series":"EN_ATM_CO2MVA"},{"Year":2016,"Value":0.37,"Units":"KG_CO2_PER_GDP_EUR","Series":"EN_ATM_CO2MVA"},{"Year":2017,"Value":0.35,"Units":"KG_CO2_PER_GDP_EUR","Series":"EN_ATM_CO2MVA"},{"Year":2018,"Value":0.36,"Units":"KG_CO2_PER_GDP_EUR","Series":"EN_ATM_CO2MVA"},{"Year":2019,"Value":0.34,"Units":"KG_CO2_PER_GDP_EUR","Series":"EN_ATM_CO2MVA"},{"Year":2020,"Value":0.37,"Units":"KG_CO2_PER_GDP_EUR","Series":"EN_ATM_CO2MVA"},{"Year":2021,"Value":0.3,"Units":"KG_CO2_PER_GDP_EUR","Series":"EN_ATM_CO2MVA"},{"Year":2022,"Value":0.33,"Units":"KG_CO2_PER_GDP_EUR","Series":"EN_ATM_CO2MVA"},{"Year":2023,"Value":0.32,"Units":"KG_CO2_PER_GDP_EUR","Series":"EN_ATM_CO2MVA"}]